{
  "id": "st-pauli",
  "meta": {
    "etiquetas": [
      "alemania",
      "bundesliga",
      "fc-st-pauli"
    ],
    "slug": "st-pauli"
  },
  "datos": {
    "nombre_completo": "Fußball-Club St. Pauli von 1910 e. V.",
    "sigla": "FCSP",
    "fundacion": "15 de mayo de 1910",
    "apodo": "Die Kiezkicker / Freibeuter der Liga (Piratas de la Liga)",
    "estadio_actual": "Millerntor-Stadion",
    "estadio_apodo": "",
    "estadio_capacidad": 29546,
    "estadio_inauguracion": "1963",
    "estadio_lat": 53.5534,
    "estadio_lng": 9.9678,
    "estadio_direccion": "Harald-Stender-Platz 1, 20359 Hamburg, Alemania",
    "socios": 30000,
    "descripcion_corta": "Club fuertemente ligado a su barrio portuario en Hamburgo y mundialmente reconocido por su sólida y combativa identidad social.",
    "paleta": [
      {
        "tag": "Marrón",
        "hex": "#533422"
      },
      {
        "tag": "Blanco",
        "hex": "#FFFFFF"
      },
      {
        "tag": "Rojo",
        "hex": "#D6001C"
      }
    ],
    "records": {
      "maximo_goleador": "André Trulsen (53)",
      "mas_presencias": "Jürgen Gronau (340)",
      "mayor_goleada": "8-1 vs Burghausen (2002)"
    },
    "nombre_oficial": "",
    "nombre_corto": "FC St. Pauli",
    "escudo_actual": "/escudos/alemania/st-pauli/st-pauli.webp",
    "historia": "El 15 de mayo de 1910 se oficializó la independencia de la sección de fútbol del club de gimnasia Hamburg-St.Pauli Turn-Verein (creado en 1862). Afincado en el vibrante barrio rojo de Hamburgo, el club trascendió lo meramente deportivo. Su historia se cimenta en cuatro grandes hitos: su progreso deportivo en la Oberliga Norte tras la Segunda Guerra Mundial; el profundo cambio cultural de los años ochenta, donde la adopción de la bandera pirata (Jolly Roger) y su fuerte postura antifascista lo convirtieron en un club de culto mundial; la recordada victoria liguera en 2002 frente al campeón intercontinental Bayern Múnich, ganándose el apodo 'Weltpokalsiegerbesieger'; y su eufórico regreso a la Bundesliga en la temporada 2023-24.",
    "idolos": [
      {
        "nombre": "André Trulsen",
        "partidos": "408",
        "goles": "11",
        "descripcion": "Jugador con el récord de presencias en el club. Defensor clave durante los ascensos a primera división."
      },
      {
        "nombre": "Fabian Boll",
        "partidos": "292",
        "goles": "29",
        "descripcion": "Mediocampista defensivo que jugó toda su carrera en el club mientras ejercía en paralelo como policía."
      },
      {
        "nombre": "Marius Ebbers",
        "partidos": "144",
        "goles": "45",
        "descripcion": "Delantero centro que resultó fundamental para el ascenso del equipo a la Bundesliga en el año 2010."
      },
      {
        "nombre": "Holger Stanislawski",
        "partidos": "260",
        "goles": "4",
        "descripcion": "Histórico jugador y posterior entrenador del club."
      },
      {
        "nombre": "Karl Miller",
        "partidos": "120",
        "goles": "0",
        "descripcion": "Histórico del club en la época previa a la Bundesliga, uno de los pocos convocados a la selección nacional."
      }
    ],
    "equipacion": [
      {
        "desde": 1910,
        "hasta": 1980,
        "c1": "#ffffff",
        "c2": "#4b2e1e",
        "sh": "#4b2e1e",
        "me": "#ffffff",
        "tipo": "liso",
        "desc": "En sus inicios, utilizaron remeras lisas blancas. El color marrón (muy poco común en el fútbol) se integraba marginalmente en los pantalones y ribetes."
      },
      {
        "desde": 1981,
        "hasta": null,
        "c1": "#4b2e1e",
        "c2": "#ffffff",
        "sh": "#ffffff",
        "me": "#4b2e1e",
        "tipo": "liso",
        "desc": "Consolidación de su identidad contracultural: instauraron la camiseta enteramente marrón oscuro como primer equipo, añadiendo esporádicamente finas líneas verticales blancas."
      }
    ]
  },
  "historia": [
    {
      "ano": "1910",
      "hito": "Rebelión Nacida Muelle Adentro en las Orillas del Puerto",
      "desc": "Temporada y campaña relevante en el historial deportivo del primer equipo."
    },
    {
      "ano": "1977",
      "hito": "Primer Ascenso a la Bundesliga",
      "desc": "Temporada y campaña relevante en el historial deportivo del primer equipo."
    },
    {
      "ano": "1980",
      "hito": "Identidad Antifascista y la Calavera",
      "desc": "Temporada y campaña relevante en el historial deportivo del primer equipo."
    },
    {
      "ano": "2002",
      "hito": "La Victoria sobre el Bayern Múnich",
      "desc": "Temporada y campaña relevante en el historial deportivo del primer equipo."
    },
    {
      "ano": "2024",
      "hito": "Campeonato y Retorno a Primera",
      "desc": "Temporada y campaña relevante en el historial deportivo del primer equipo."
    }
  ],
  "canchas": [
    {
      "nombre": "Millerntor-Stadion (Wilhelm-Koch-Stadion 1970-1998)",
      "capacidad": "29.546",
      "inauguracion": "1963",
      "url": "https://www.google.com/maps/search/?api=1&query=53.554444,9.967778",
      "direccion": "Harald-Stender-Platz 1, 20359 Hamburg, Alemania",
      "descripcion": "El corazón pirata, antifascista y contracultural de Hamburgo. La directiva y socios tienen estrictamente prohibido vender los 'naming rights' institucionales, defendiendo a muerte la denominación Millerntor.",
      "lat": 53.554444,
      "lng": 9.967778
    }
  ],
  "equipacion": [
    {
      "desde": 1910,
      "hasta": null,
      "c1": "#4a2511",
      "c2": "#ffffff",
      "sh": "#4a2511",
      "me": "#4a2511",
      "tipo": "liso",
      "desc": "Estilo clásico utilizado habitualmente por el club durante esta época."
    }
  ],
  "idolos": [
    {
      "nombre": "Fabian Boll",
      "periodo": "2002-2014",
      "pos": "Mediocampista",
      "desc": "Histórico mediocampista central de destacada labor recuperadora y posicional que logró alternar su extensa trayectoria oficial deportiva combinándola con su profesión en las fuerzas policiales."
    },
    {
      "nombre": "André Trulsen",
      "periodo": "1986-2001",
      "pos": "Defensor",
      "desc": "Sólido defensor inamovible de enorme recorrido competitivo y liguero. Ostenta la sumatoria récord garantizando su lugar como el jugador con mayor número de participaciones de la institución."
    },
    {
      "nombre": "Holger Stanislawski",
      "periodo": "1993-2004",
      "pos": "Defensor",
      "desc": "Férreo defensor titular organizador. Condujo la zona baja rígidamente asegurando posiciones y más tarde lideró a la plantilla asumiendo exitosamente el rol oficial como entrenador."
    },
    {
      "nombre": "Marius Ebbers",
      "periodo": "2008-2013",
      "pos": "Delantero",
      "desc": "Centrodelantero oportunista que anotó las suficientes cifras logrando sobrepasar la cifra de un centenar de anotaciones asegurando destacadas contiendas propiciando ascensos de categoría al primer nivel."
    },
    {
      "nombre": "Walter Frosch",
      "periodo": "1976-1982",
      "pos": "Defensor",
      "desc": "Zaguero de enorme temperamento en el campo. Se consolidó como recordada figura defensiva institucional mostrando inclaudicable firmeza en los difíciles certámenes y logrando enorme recordación popular estable."
    }
  ],
  "goleadores_historicos": [
    {
      "nombre": "Franz Gerber",
      "goles": 52,
      "periodo": "1976-1978",
      "partidos": 77,
      "desc": "Atacante destacado en los registros del club. Convirtió un total de 52 goles en competiciones oficiales durante su trayectoria en el equipo entre 1976-1978."
    },
    {
      "nombre": "Marius Ebbers",
      "goles": 43,
      "periodo": "2008-2013",
      "partidos": 148,
      "desc": "Atacante destacado en los registros del club. Convirtió un total de 43 goles en competiciones oficiales durante su trayectoria en el equipo entre 2008-2013."
    },
    {
      "nombre": "Rouwen Hennings",
      "goles": 35,
      "periodo": "2008-2012",
      "partidos": 131,
      "desc": "Atacante destacado en los registros del club. Convirtió un total de 35 goles en competiciones oficiales durante su trayectoria en el equipo entre 2008-2012."
    },
    {
      "nombre": "Guido Burgstaller",
      "goles": 31,
      "periodo": "2020-2022",
      "partidos": 60,
      "desc": "Atacante destacado en los registros del club. Convirtió un total de 31 goles en competiciones oficiales durante su trayectoria en el equipo entre 2020-2022."
    },
    {
      "nombre": "Alexander Meier",
      "goles": 18,
      "periodo": "2001-2019",
      "partidos": 70,
      "desc": "Atacante destacado en los registros del club. Convirtió un total de 18 goles en competiciones oficiales durante su trayectoria en el equipo entre 2001-2019."
    }
  ],
  "presencias_historicas": [
    {
      "nombre": "André Trulsen",
      "partidos": 408,
      "periodo": "1986-2001",
      "desc": "Jugador con alta regularidad en la historia de la entidad. Registró un total de 408 partidos disputados, manteniendo presencia oficial ininterrumpida entre 1986-2001."
    },
    {
      "nombre": "Jürgen Gronau",
      "partidos": 333,
      "periodo": "1984-1997",
      "desc": "Jugador con alta regularidad en la historia de la entidad. Registró un total de 333 partidos disputados, manteniendo presencia oficial ininterrumpida entre 1984-1997."
    },
    {
      "nombre": "Fabian Boll",
      "partidos": 292,
      "periodo": "2002-2014",
      "desc": "Jugador con alta regularidad en la historia de la entidad. Registró un total de 292 partidos disputados, manteniendo presencia oficial ininterrumpida entre 2002-2014."
    },
    {
      "nombre": "Holger Stanislawski",
      "partidos": 260,
      "periodo": "1993-2004",
      "desc": "Jugador con alta regularidad en la historia de la entidad. Registró un total de 260 partidos disputados, manteniendo presencia oficial ininterrumpida entre 1993-2004."
    },
    {
      "nombre": "Jan-Philipp Kalla",
      "partidos": 164,
      "periodo": "2006-2020",
      "desc": "Jugador con alta regularidad en la historia de la entidad. Registró un total de 164 partidos disputados, manteniendo presencia oficial ininterrumpida entre 2006-2020."
    }
  ],
  "titulos": [
    {
      "nombre": "2. Bundesliga",
      "cantidad": 2,
      "anios": [
        "1976-77",
        "2023-24"
      ]
    }
  ],
  "evolucion_escudos": [
    {
      "ano": "",
      "url": "/escudos/alemania/st-pauli/FC_St__Pauli_logo.svg"
    },
    {
      "ano": "Actualidad",
      "url": "/escudos/alemania/st-pauli/st-pauli.webp"
    }
  ],
  "origen_apodos": [
    {
      "apodo": "Die Kiezkicker",
      "origen": "Consagrado y validado sociológicamente por abarcar la profunda bohemia local de toda su cuna, afincada en la barriada portuaria roja y obrera de Hamburgo (Reeperbahn). Los vecinos siempre la llamaron coloquialmente Kiez, y la prensa generalizó referenciarlos para la eternidad de manera barrial como Los Pateadores de Kiez (o Los Pateadores del Barrio)."
    }
  ],
  "h2h": {
    "bayern-munchen": {
      "pj": 1,
      "pg": 0,
      "pe": 0,
      "pp": 1
    },
    "koln": {
      "pj": 1,
      "pg": 0,
      "pe": 1,
      "pp": 0
    }
  },
  "ultima_actualizacion": "2026-04-20T10:07:47.711Z"
}