{
  "id": "aldosivi",
  "datos": {
    "nombre_oficial": "Club Atlético Aldosivi",
    "nombre_corto": "Aldosivi",
    "apodos": [
      "El Tiburón",
      "El Millonario del Sur"
    ],
    "fundacion": "1913-03-14",
    "ciudad": "Mar del Plata",
    "pais": "Argentina",
    "estadio_actual": "Estadio José María Minella",
    "estadio_capacidad": 20000,
    "estadio_lat": -37.9851,
    "estadio_lng": -57.5737,
    "debut_primera": 2013
  },
  "equipacion": {
    "titular": {
      "colores": [
        "#228B22",
        "#FFFFFF"
      ],
      "diseno": "unicolor_verde"
    },
    "short": "#228B22",
    "medias": "#228B22"
  },
  "titulos_primera": 0,
  "meta": {
    "datos_completos": false
  }
}